{"title":"Maroon 5 feat. Rihanna - If I Never See Your Face Again","uid":4233253,"size":132433924,"categoryP":"video","categoryS":"music_videos","magnet":"?xt=urn:btih:0042aba0ce36709d428655d8605b696295a683db&amp;dn=Maroon+5+feat.+Rihanna+-+If+I+Never+See+Your+Face+Again&amp;tr=udp%3A%2F%2Ftracker.openbittorrent.com%3A80&amp;tr=udp%3A%2F%2Fopen.demonii.com%3A1337&amp;tr=udp%3A%2F%2Ftracker.coppersurfer.tk%3A6969&amp;tr=udp%3A%2F%2Fexodus.desync.com%3A6969","seeders":0,"leechers":1,"uploader":"2nafish","files":1,"time":1213169565,"description":"Source: TV\n\nFile Info:\n\nVideo: MPEG-2 video , 720x480, 29.97 fps, VBR (Constant quality), Maximum 6124 kbps\nAudio: Dolby Digital, 48000 Hz, Stereo, 448 kbps\n\n\n\n\n\n\n\n\n\n\n\n\n\nMy Videos:\n &lt;a href=&quot;\nhttp://thepiratebay.se/user/2nafish/&quot; rel=&quot;nofollow&quot; target=&quot;_NEW&quot;&gt;\nhttp://thepiratebay.se/user/2nafish/&lt;/a&gt;","torrent":{"xt":"urn:btih:0042aba0ce36709d428655d8605b696295a683db","amp;dn":"Maroon+5+feat.+Rihanna+-+If+I+Never+See+Your+Face+Again","amp;tr":["udp%3A%2F%2Ftracker.openbittorrent.com%3A80","udp%3A%2F%2Fopen.demonii.com%3A1337","udp%3A%2F%2Ftracker.coppersurfer.tk%3A6969","udp%3A%2F%2Fexodus.desync.com%3A6969"],"infoHash":"0042aba0ce36709d428655d8605b696295a683db","infoHashBuffer":{"type":"Buffer","data":[0,66,171,160,206,54,112,157,66,134,85,216,96,91,105,98,149,166,131,219]},"announce":[],"urlList":[]}}