{"title":"Pietra.wmv","uid":4183845,"size":213363970,"categoryP":"porn","categoryS":"movie_clips","magnet":"?xt=urn:btih:2098adea186d9d8dbc5269ebccc7a70db1709fda&amp;dn=Pietra.wmv&amp;tr=udp%3A%2F%2Ftracker.openbittorrent.com%3A80&amp;tr=udp%3A%2F%2Fopen.demonii.com%3A1337&amp;tr=udp%3A%2F%2Ftracker.coppersurfer.tk%3A6969&amp;tr=udp%3A%2F%2Fexodus.desync.com%3A6969","seeders":0,"leechers":1,"uploader":"dsfsdfsw","files":1,"time":1210554356,"description":"op","torrent":{"xt":"urn:btih:2098adea186d9d8dbc5269ebccc7a70db1709fda","amp;dn":"Pietra.wmv","amp;tr":["udp%3A%2F%2Ftracker.openbittorrent.com%3A80","udp%3A%2F%2Fopen.demonii.com%3A1337","udp%3A%2F%2Ftracker.coppersurfer.tk%3A6969","udp%3A%2F%2Fexodus.desync.com%3A6969"],"infoHash":"2098adea186d9d8dbc5269ebccc7a70db1709fda","infoHashBuffer":{"type":"Buffer","data":[32,152,173,234,24,109,157,141,188,82,105,235,204,199,167,13,177,112,159,218]},"announce":[],"urlList":[]}}