{"title":"The land of Attaf[DVDRIP]-Johonievision","uid":4209782,"size":4284520448,"categoryP":"video","categoryS":"movies_dvdr","magnet":"?xt=urn:btih:21e51afa1587dd3f7f5f3b18f71ea86748aa78ab&amp;dn=The+land+of+Attaf%5BDVDRIP%5D-Johonievision&amp;tr=udp%3A%2F%2Ftracker.openbittorrent.com%3A80&amp;tr=udp%3A%2F%2Fopen.demonii.com%3A1337&amp;tr=udp%3A%2F%2Ftracker.coppersurfer.tk%3A6969&amp;tr=udp%3A%2F%2Fexodus.desync.com%3A6969","seeders":0,"leechers":0,"uploader":"johonievision","files":14,"time":1212002867,"description":"The movie tackles a part of the life of the Prophet&amp;#039;s grandson Imam Hussein peace be upon them.Starting from the taking over of the rule by Yazid in Sham and the dispatching to his ruler in Medina demanding taking from him the oath of fealty from Imam Hussein and the Imam&amp;#039;s procession towards Karbala.The movie highlights the general situation in Medina and then in Holy Mecca and the attitude of the people of Kufa from the Imam&amp;#039;s movement.The film portrays the battle of Karbala and the martyrdom of Imam Hussein and those acconpanying him.     Spoken language Arabic with english and french subtitles.Enjoy!!!","torrent":{"xt":"urn:btih:21e51afa1587dd3f7f5f3b18f71ea86748aa78ab","amp;dn":"The+land+of+Attaf%5BDVDRIP%5D-Johonievision","amp;tr":["udp%3A%2F%2Ftracker.openbittorrent.com%3A80","udp%3A%2F%2Fopen.demonii.com%3A1337","udp%3A%2F%2Ftracker.coppersurfer.tk%3A6969","udp%3A%2F%2Fexodus.desync.com%3A6969"],"infoHash":"21e51afa1587dd3f7f5f3b18f71ea86748aa78ab","infoHashBuffer":{"type":"Buffer","data":[33,229,26,250,21,135,221,63,127,95,59,24,247,30,168,103,72,170,120,171]},"announce":[],"urlList":[]}}