{"title":"Gay Ass Pounding Hunks","uid":4214003,"size":43519536,"categoryP":"porn","categoryS":"movie_clips","magnet":"?xt=urn:btih:23255b16db1952b8b38809e92e8b43f7838db343&amp;dn=Gay+Ass+Pounding+Hunks&amp;tr=udp%3A%2F%2Ftracker.openbittorrent.com%3A80&amp;tr=udp%3A%2F%2Fopen.demonii.com%3A1337&amp;tr=udp%3A%2F%2Ftracker.coppersurfer.tk%3A6969&amp;tr=udp%3A%2F%2Fexodus.desync.com%3A6969","seeders":0,"leechers":1,"uploader":"TopsyCrett","files":1,"time":1212234458,"description":"Look at the size of that picnic BASKET","torrent":{"xt":"urn:btih:23255b16db1952b8b38809e92e8b43f7838db343","amp;dn":"Gay+Ass+Pounding+Hunks","amp;tr":["udp%3A%2F%2Ftracker.openbittorrent.com%3A80","udp%3A%2F%2Fopen.demonii.com%3A1337","udp%3A%2F%2Ftracker.coppersurfer.tk%3A6969","udp%3A%2F%2Fexodus.desync.com%3A6969"],"infoHash":"23255b16db1952b8b38809e92e8b43f7838db343","infoHashBuffer":{"type":"Buffer","data":[35,37,91,22,219,25,82,184,179,136,9,233,46,139,67,247,131,141,179,67]},"announce":[],"urlList":[]}}