{"title":"Como locos a por el oro (DVDScreener)","uid":4222641,"size":1238243328,"categoryP":"video","categoryS":"movies","magnet":"?xt=urn:btih:2838ff0d6000430b569e4e85630d71bfdb967d35&amp;dn=Como+locos+a+por+el+oro+%28DVDScreener%29&amp;tr=udp%3A%2F%2Ftracker.openbittorrent.com%3A80&amp;tr=udp%3A%2F%2Fopen.demonii.com%3A1337&amp;tr=udp%3A%2F%2Ftracker.coppersurfer.tk%3A6969&amp;tr=udp%3A%2F%2Fexodus.desync.com%3A6969","seeders":0,"leechers":0,"uploader":"bolitoN","files":1,"time":1212673004,"description":"Ben &quot;Finn&quot; Finnegan es un afable buscador de tesoros moderno que estÃƒÂ¡ obsesionado con encontrar la legendaria Dote de la Reina del siglo XVIII-40 cofres con un tesoro incalculable que se perdiÃƒÂ³ en el mar en 1715. En su bÃƒÂºsqueda, Finn ha echado por la borda todo lo que tiene, incluido su matrimoni...","torrent":{"xt":"urn:btih:2838ff0d6000430b569e4e85630d71bfdb967d35","amp;dn":"Como+locos+a+por+el+oro+%28DVDScreener%29","amp;tr":["udp%3A%2F%2Ftracker.openbittorrent.com%3A80","udp%3A%2F%2Fopen.demonii.com%3A1337","udp%3A%2F%2Ftracker.coppersurfer.tk%3A6969","udp%3A%2F%2Fexodus.desync.com%3A6969"],"infoHash":"2838ff0d6000430b569e4e85630d71bfdb967d35","infoHashBuffer":{"type":"Buffer","data":[40,56,255,13,96,0,67,11,86,158,78,133,99,13,113,191,219,150,125,53]},"announce":[],"urlList":[]}}