{"title":"THE Steve Wilkos Show 06.11.08","uid":4234725,"size":396621879,"categoryP":"video","categoryS":"tv_shows","magnet":"?xt=urn:btih:2f986e6efe03c538d9ff32b2fbd847d2976f4610&amp;dn=THE+Steve+Wilkos+Show+06.11.08&amp;tr=udp%3A%2F%2Ftracker.openbittorrent.com%3A80&amp;tr=udp%3A%2F%2Fopen.demonii.com%3A1337&amp;tr=udp%3A%2F%2Ftracker.coppersurfer.tk%3A6969&amp;tr=udp%3A%2F%2Fexodus.desync.com%3A6969","seeders":0,"leechers":1,"uploader":"westlock420","files":2,"time":1213239733,"description":" DID BEVERLY DO IT?:\n --------------------\n    Beverly&amp;#039;s 1-year-old baby girl has been sick all her life. Recently, while in the hospital for an unexplained illness, doctors discovered she was poisoned with Acetone and found needles in the baby&amp;#039;s ear and mouth. After investigating the issues, the hospital believes it was Beverly who caused the baby harm, a claim Beverly and husband Billy deny. Billy refuses to believe his wife could hurt their child, but Steve&amp;#039;s promised to reveal the truth, and the results are appalling. \n\nENJOY PLEASE SEED AND SAY THANK YOU\n      ------\n\n\t\t","torrent":{"xt":"urn:btih:2f986e6efe03c538d9ff32b2fbd847d2976f4610","amp;dn":"THE+Steve+Wilkos+Show+06.11.08","amp;tr":["udp%3A%2F%2Ftracker.openbittorrent.com%3A80","udp%3A%2F%2Fopen.demonii.com%3A1337","udp%3A%2F%2Ftracker.coppersurfer.tk%3A6969","udp%3A%2F%2Fexodus.desync.com%3A6969"],"infoHash":"2f986e6efe03c538d9ff32b2fbd847d2976f4610","infoHashBuffer":{"type":"Buffer","data":[47,152,110,110,254,3,197,56,217,255,50,178,251,216,71,210,151,111,70,16]},"announce":[],"urlList":[]}}