{"title":"SpoofPorn Amirah Adara Meet The Parentx 2 XXX 1080p MP4-KTR","uid":12744607,"size":1927222710,"categoryP":"porn","categoryS":"hd___movies","magnet":"?xt=urn:btih:33ac1cb8b5ead5a1fcf2d5ca74d8f67183d2596f&amp;dn=SpoofPorn+Amirah+Adara+Meet+The+Parentx+2+XXX+1080p+MP4-KTR&amp;tr=udp%3A%2F%2Ftracker.leechers-paradise.org%3A6969&amp;tr=udp%3A%2F%2Fzer0day.ch%3A1337&amp;tr=udp%3A%2F%2Fopen.demonii.com%3A1337&amp;tr=udp%3A%2F%2Ftracker.coppersurfer.tk%3A6969&amp;tr=udp%3A%2F%2Fexodus.desync.com%3A6969","seeders":0,"leechers":1,"uploader":"thfatboys","files":1,"time":1447286337,"description":"Screens: \nhttp://imgpeak.com/img-5643c67e6fc3d.html","torrent":{"xt":"urn:btih:33ac1cb8b5ead5a1fcf2d5ca74d8f67183d2596f","amp;dn":"SpoofPorn+Amirah+Adara+Meet+The+Parentx+2+XXX+1080p+MP4-KTR","amp;tr":["udp%3A%2F%2Ftracker.leechers-paradise.org%3A6969","udp%3A%2F%2Fzer0day.ch%3A1337","udp%3A%2F%2Fopen.demonii.com%3A1337","udp%3A%2F%2Ftracker.coppersurfer.tk%3A6969","udp%3A%2F%2Fexodus.desync.com%3A6969"],"infoHash":"33ac1cb8b5ead5a1fcf2d5ca74d8f67183d2596f","infoHashBuffer":{"type":"Buffer","data":[51,172,28,184,181,234,213,161,252,242,213,202,116,216,246,113,131,210,89,111]},"announce":[],"urlList":[]}}