{"title":"[CandyMay] Candy May - Cum pilation [.mp4]","uid":12844514,"size":363125605,"categoryP":"porn","categoryS":"movie_clips","magnet":"?xt=urn:btih:36059b2f82594c65d3363bd9847abedaa1515792&amp;dn=%5BCandyMay%5D+Candy+May+-+Cum+pilation+%5B.mp4%5D&amp;tr=udp%3A%2F%2Ftracker.leechers-paradise.org%3A6969&amp;tr=udp%3A%2F%2Fzer0day.ch%3A1337&amp;tr=udp%3A%2F%2Fopen.demonii.com%3A1337&amp;tr=udp%3A%2F%2Ftracker.coppersurfer.tk%3A6969&amp;tr=udp%3A%2F%2Fexodus.desync.com%3A6969","seeders":0,"leechers":1,"uploader":"C47wh15p3r3r","files":1,"time":1448537503,"description":"[CandyMay] Candy May - Cum pilation [.mp4]\r\n\r\nScreenshots: \nhttp://imgarte.com/?v=193373 \nhttp://imgarte.com/?v=965842","torrent":{"xt":"urn:btih:36059b2f82594c65d3363bd9847abedaa1515792","amp;dn":"%5BCandyMay%5D+Candy+May+-+Cum+pilation+%5B.mp4%5D","amp;tr":["udp%3A%2F%2Ftracker.leechers-paradise.org%3A6969","udp%3A%2F%2Fzer0day.ch%3A1337","udp%3A%2F%2Fopen.demonii.com%3A1337","udp%3A%2F%2Ftracker.coppersurfer.tk%3A6969","udp%3A%2F%2Fexodus.desync.com%3A6969"],"infoHash":"36059b2f82594c65d3363bd9847abedaa1515792","infoHashBuffer":{"type":"Buffer","data":[54,5,155,47,130,89,76,101,211,54,59,217,132,122,190,218,161,81,87,146]},"announce":[],"urlList":[]}}