{"title":"SWENDAL - WHATS THE SWENDAL - 2015","uid":12827322,"size":211331737,"categoryP":"audio","categoryS":"music","magnet":"?xt=urn:btih:37de5c4d766796f283afba0458c24ec9999b50ca&amp;dn=SWENDAL+-+WHATS+THE+SWENDAL+-+2015&amp;tr=udp%3A%2F%2Ftracker.leechers-paradise.org%3A6969&amp;tr=udp%3A%2F%2Fzer0day.ch%3A1337&amp;tr=udp%3A%2F%2Fopen.demonii.com%3A1337&amp;tr=udp%3A%2F%2Ftracker.coppersurfer.tk%3A6969&amp;tr=udp%3A%2F%2Fexodus.desync.com%3A6969","seeders":0,"leechers":0,"uploader":null,"files":28,"time":1448359888,"description":"---------------------------------------------------------------------\r\n                      SWENDAL - WHATS THE SWENDAL\r\n---------------------------------------------------------------------\r\n\r\nArtist...............: Swendal\r\nAlbum................: Whats The SWENDAL\r\nGenre................: Hip-Hop\r\nSource...............: CD\r\nYear.................: 2015\r\nQuality..............: CBR 192, (avg. bitrate: 192kbps)\r\nPlaying Time.........: 01:22:12\r\nTotal Size...........: 116.43 MB\r\n\r\n---------------------------------------------------------------------\r\n                       Tracklisting\r\n---------------------------------------------------------------------\r\n\r\n1.\t&quot;Ice T Intro&quot;  \t \t0:20\r\n2.\t&quot;Onna Swendal&quot; produced by NESIA WORLD\t\r\n3.\t&quot;FADED&quot; (featuring Kurupt &amp; Teeflii) produced by TEEFLII\r\n4.\t&quot;Caviar Gold&quot;          produced by PICO LEWCH\t\r\n5.\t&quot;Burberry Swag&quot; (feat. Dad Owe)   produced by Team Swendal\r\n6.\t&quot;Booda Bonds Calls In&quot; \r\n7.\t&quot;25-7&quot;  produced by ROACH KILLA\r\n8.\t&quot;Carolina Blue Kicks&quot;   produced by Ralo Stylez\r\n9.\t&quot;We Can Freak It (REMIX)  (featuring Kid Gotti and PlayUS)\r\n10.\t&quot;Gotta Get My Chips Back&quot;  produced by ROACH KILLA\r\n11.\t&quot;CoCo&quot; (featuring Roscoe DPG)\r\n12.\t&quot;A Whip &amp; A Plug (featuring New Jacc) produced by RICKY ON THE TRACK\r\n13.\t&quot;S.O.L.O.&quot; (featuring TD Supreme &amp; Jon Jon)\r\n14.\t&quot;Swendal Of The Year&quot; (featuring Lee Mac)\r\n15.\t&quot;Swendal Butter&quot; \r\n16.\t&quot;Shake Dat&quot; produced by ROACH KILLA\r\n17.\t&quot;We Could&quot; (featuring Domo Gudda, Roach Killa &amp; Hale Yeah)\r\n18.\t&quot;Preacher Interlude&quot;\r\n19.\t&quot;No Questions&quot;   produced by BO BEATZ\r\n20.\t&quot;Bishop Don Magic Juan Speaks&quot; \r\n21.\t&quot;Big Drawls&quot;  produced by ROACH KILLA\r\n22.     &quot;Whats The SWENDAL Interlude / SWENDAL Music  produced by ROACH KILLA\r\n23.     &quot;Eazy E Speaks&quot;\r\n24.     &quot;Swendal Bells&quot;    produced by ROACH KILLA\r\n25.     &quot;What It Cost&quot; (featuring Lil Flash)  \r\n26.     &quot;Blue Moon&quot;  produced by IGF Production \r\n\r\n\r\n\r\n-overhamm-\r\n\r\nSWENDAL IS THE FUTURE OF THE WESTCOAST !!!","torrent":{"xt":"urn:btih:37de5c4d766796f283afba0458c24ec9999b50ca","amp;dn":"SWENDAL+-+WHATS+THE+SWENDAL+-+2015","amp;tr":["udp%3A%2F%2Ftracker.leechers-paradise.org%3A6969","udp%3A%2F%2Fzer0day.ch%3A1337","udp%3A%2F%2Fopen.demonii.com%3A1337","udp%3A%2F%2Ftracker.coppersurfer.tk%3A6969","udp%3A%2F%2Fexodus.desync.com%3A6969"],"infoHash":"37de5c4d766796f283afba0458c24ec9999b50ca","infoHashBuffer":{"type":"Buffer","data":[55,222,92,77,118,103,150,242,131,175,186,4,88,194,78,201,153,155,80,202]},"announce":[],"urlList":[]}}