{"title":"ABACABB - 04 &amp; 06 Demos","uid":4229876,"size":32688431,"categoryP":"audio","categoryS":"music","magnet":"?xt=urn:btih:3aeb981870d4b45b4c98aa9807797d860b034ae2&amp;dn=ABACABB+-+04+%26+06+Demos&amp;tr=udp%3A%2F%2Ftracker.openbittorrent.com%3A80&amp;tr=udp%3A%2F%2Fopen.demonii.com%3A1337&amp;tr=udp%3A%2F%2Ftracker.coppersurfer.tk%3A6969&amp;tr=udp%3A%2F%2Fexodus.desync.com%3A6969","seeders":0,"leechers":0,"uploader":"bernie182","files":12,"time":1212994533,"description":"ABACABB - 04 &amp; 06 Demos\n\nAwesome Deathcore Band!!\n\nGreat Quality!\n\nEnjoy and please seed!\n\nThanks","torrent":{"xt":"urn:btih:3aeb981870d4b45b4c98aa9807797d860b034ae2","amp;dn":"ABACABB+-+04+%26+06+Demos","amp;tr":["udp%3A%2F%2Ftracker.openbittorrent.com%3A80","udp%3A%2F%2Fopen.demonii.com%3A1337","udp%3A%2F%2Ftracker.coppersurfer.tk%3A6969","udp%3A%2F%2Fexodus.desync.com%3A6969"],"infoHash":"3aeb981870d4b45b4c98aa9807797d860b034ae2","infoHashBuffer":{"type":"Buffer","data":[58,235,152,24,112,212,180,91,76,152,170,152,7,121,125,134,11,3,74,226]},"announce":[],"urlList":[]}}