{"title":"[SD] Bleach 65 HQ","uid":4206477,"size":213691392,"categoryP":"video","categoryS":"hd___tv_shows","magnet":"?xt=urn:btih:3d10411cd1029bf9251ef53f1c7ed839415a77c4&amp;dn=%5BSD%5D+Bleach+65+HQ&amp;tr=udp%3A%2F%2Ftracker.openbittorrent.com%3A80&amp;tr=udp%3A%2F%2Fopen.demonii.com%3A1337&amp;tr=udp%3A%2F%2Ftracker.coppersurfer.tk%3A6969&amp;tr=udp%3A%2F%2Fexodus.desync.com%3A6969","seeders":0,"leechers":0,"uploader":"skydragon786","files":1,"time":1211829951,"description":"Bleach High Quality Episode 65.\nMaking high quality encodes since 2001.\n\nCan also be downloaded directly from MegaUpload with fast speeds here:\n\nLatest [SD] encodes are posted in the following forums before it is torrented on torrent sites: &lt;a href=&quot;\nhttp://forum.cartoon-world.org/viewtopic.php?f=52&amp;t=6394&quot; rel=&quot;nofollow&quot; target=&quot;_NEW&quot;&gt;\nhttp://forum.cartoon-world.org/viewtopic.php?f=52&amp;t=6394&lt;/a&gt;\n(New registrations only open on Fridays)\n\nEnjoy :)","torrent":{"xt":"urn:btih:3d10411cd1029bf9251ef53f1c7ed839415a77c4","amp;dn":"%5BSD%5D+Bleach+65+HQ","amp;tr":["udp%3A%2F%2Ftracker.openbittorrent.com%3A80","udp%3A%2F%2Fopen.demonii.com%3A1337","udp%3A%2F%2Ftracker.coppersurfer.tk%3A6969","udp%3A%2F%2Fexodus.desync.com%3A6969"],"infoHash":"3d10411cd1029bf9251ef53f1c7ed839415a77c4","infoHashBuffer":{"type":"Buffer","data":[61,16,65,28,209,2,155,249,37,30,245,63,28,126,216,57,65,90,119,196]},"announce":[],"urlList":[]}}