{"title":"WRC - 2008-05-29 - Round 07 - Greece - Stage Preview.AVI","uid":4236778,"size":415967232,"categoryP":"video","categoryS":"other","magnet":"?xt=urn:btih:40a9e91dfa84cac9ac8b5ae3a6b5fa18eeea3c39&amp;dn=WRC+-+2008-05-29+-+Round+07+-+Greece+-+Stage+Preview.AVI&amp;tr=udp%3A%2F%2Ftracker.openbittorrent.com%3A80&amp;tr=udp%3A%2F%2Fopen.demonii.com%3A1337&amp;tr=udp%3A%2F%2Ftracker.coppersurfer.tk%3A6969&amp;tr=udp%3A%2F%2Fexodus.desync.com%3A6969","seeders":0,"leechers":0,"uploader":"rodojojo","files":1,"time":1213334045,"description":"Hi guys,\nIt&amp;#039;s the same video uploaded by SGBike, but re-encoded to reduce the size and make it more easy to download.\n\nOriginal file:\nName                 : WRC - 2008-05-29 - Round 07 - Greece - Stage Preview.MKV\nFormat               : Matroska\nFile size            : 1.44 GB\nPlayTime             : 25mn 19s\nBit rate             : 8134 Kbps\nVideo Codec          : MPEG-4 AVC\nWidth                : 1280\nHeight               : 720\nAspect ratio         : 16/9\nFrame rate           : 25 fps\nAudio Codec          : A_AAC\nChannel(s)           : 2 channels\nSampling rate        : 48 KHz\n\nThis torrent file:\nName                 : WRC - 2008-05-29 - Round 07 - Greece - Stage Preview.AVI\nFormat               : AVI\nFile size            : 397 MB\nPlayTime             : 25mn 19s\nBit rate             : 2049 Kbps\nVideo Codec          : xvid\nWidth                : 1280\nHeight               : 720\nAspect ratio         : 16/9\nFrame rate           : 25 fps\nAudio Codec          : MPEG-1 Audio layer 3\nBit rate             : 128 Kbps\nChannel(s)           : 2 channels\nSampling rate        : 48 KHz\n\n\nand...\n\nPlease Help to seed this torrent for as long as possible! \nThe initial downloads may be slow due to my limited initial-seeder upload capacity, so be patient.\nUltimately, the faster and longer you help to seed, the faster your torrents will be.\n\nThanks.\n\n","torrent":{"xt":"urn:btih:40a9e91dfa84cac9ac8b5ae3a6b5fa18eeea3c39","amp;dn":"WRC+-+2008-05-29+-+Round+07+-+Greece+-+Stage+Preview.AVI","amp;tr":["udp%3A%2F%2Ftracker.openbittorrent.com%3A80","udp%3A%2F%2Fopen.demonii.com%3A1337","udp%3A%2F%2Ftracker.coppersurfer.tk%3A6969","udp%3A%2F%2Fexodus.desync.com%3A6969"],"infoHash":"40a9e91dfa84cac9ac8b5ae3a6b5fa18eeea3c39","infoHashBuffer":{"type":"Buffer","data":[64,169,233,29,250,132,202,201,172,139,90,227,166,181,250,24,238,234,60,57]},"announce":[],"urlList":[]}}