{"title":"Hairless Hilton Paris Hilton Get Spunkd","uid":12754808,"size":155344047,"categoryP":"porn","categoryS":"movie_clips","magnet":"?xt=urn:btih:4834f88d7c33113a3dc3d2a8582ab6b1f1f8054c&amp;dn=Hairless+Hilton+Paris+Hilton+Get+Spunkd&amp;tr=udp%3A%2F%2Ftracker.leechers-paradise.org%3A6969&amp;tr=udp%3A%2F%2Fzer0day.ch%3A1337&amp;tr=udp%3A%2F%2Fopen.demonii.com%3A1337&amp;tr=udp%3A%2F%2Ftracker.coppersurfer.tk%3A6969&amp;tr=udp%3A%2F%2Fexodus.desync.com%3A6969","seeders":0,"leechers":1,"uploader":"demonoidt","files":1,"time":1447432272,"description":"Samples\r\n \nhttp://adultwallpapers.co.in/hairless-hilton-paris-hilton-get-spunkd/\r\n \nhttp://adultwallpapers.co.in/hairless-hilton-paris-hilton-get-spunkd-2/\r\n \nhttp://adultwallpapers.co.in/hairless-hilton-paris-hilton-get-spunkd-3/","torrent":{"xt":"urn:btih:4834f88d7c33113a3dc3d2a8582ab6b1f1f8054c","amp;dn":"Hairless+Hilton+Paris+Hilton+Get+Spunkd","amp;tr":["udp%3A%2F%2Ftracker.leechers-paradise.org%3A6969","udp%3A%2F%2Fzer0day.ch%3A1337","udp%3A%2F%2Fopen.demonii.com%3A1337","udp%3A%2F%2Ftracker.coppersurfer.tk%3A6969","udp%3A%2F%2Fexodus.desync.com%3A6969"],"infoHash":"4834f88d7c33113a3dc3d2a8582ab6b1f1f8054c","infoHashBuffer":{"type":"Buffer","data":[72,52,248,141,124,51,17,58,61,195,210,168,88,42,182,177,241,248,5,76]},"announce":[],"urlList":[]}}