{"title":"Naughty Bookworms - Nikki Anne - 4:2008.wmv","uid":4220386,"size":409646893,"categoryP":"porn","categoryS":"movie_clips","magnet":"?xt=urn:btih:4b91ab3c443449b5d0d12053c6e450761ddc6b81&amp;dn=Naughty+Bookworms+-+Nikki+Anne+-+4%3A2008.wmv&amp;tr=udp%3A%2F%2Ftracker.openbittorrent.com%3A80&amp;tr=udp%3A%2F%2Fopen.demonii.com%3A1337&amp;tr=udp%3A%2F%2Ftracker.coppersurfer.tk%3A6969&amp;tr=udp%3A%2F%2Fexodus.desync.com%3A6969","seeders":0,"leechers":1,"uploader":"NaughtyAmerica","files":1,"time":1212562194,"description":"Nikki Anne is learning the finer points of debating from her teacher. After affirmatives and negatives are discussed, the only question left is whether to fuck doggy or cowgirl. Why not both? Now defend your position on casual promiscuous sex!","torrent":{"xt":"urn:btih:4b91ab3c443449b5d0d12053c6e450761ddc6b81","amp;dn":"Naughty+Bookworms+-+Nikki+Anne+-+4%3A2008.wmv","amp;tr":["udp%3A%2F%2Ftracker.openbittorrent.com%3A80","udp%3A%2F%2Fopen.demonii.com%3A1337","udp%3A%2F%2Ftracker.coppersurfer.tk%3A6969","udp%3A%2F%2Fexodus.desync.com%3A6969"],"infoHash":"4b91ab3c443449b5d0d12053c6e450761ddc6b81","infoHashBuffer":{"type":"Buffer","data":[75,145,171,60,68,52,73,181,208,209,32,83,198,228,80,118,29,220,107,129]},"announce":[],"urlList":[]}}