{"title":"Fucking Her Blonde Sex Doll Angelina","uid":12736140,"size":95540389,"categoryP":"porn","categoryS":"movie_clips","magnet":"?xt=urn:btih:5a94fdb8eba811f05dbb61592953b4a43007aed8&amp;dn=Fucking+Her+Blonde+Sex+Doll+Angelina+PIR%40TE&amp;tr=udp%3A%2F%2Ftracker.leechers-paradise.org%3A6969&amp;tr=udp%3A%2F%2Fzer0day.ch%3A1337&amp;tr=udp%3A%2F%2Fopen.demonii.com%3A1337&amp;tr=udp%3A%2F%2Ftracker.coppersurfer.tk%3A6969&amp;tr=udp%3A%2F%2Fexodus.desync.com%3A6969","seeders":0,"leechers":1,"uploader":"Piratepr0n","files":1,"time":1447181294,"description":"-------------------------------------------------------------------------------------\nName:\nFucking Her Blonde Sex Doll Angelina   \n  --------------------\nFile list:\nFucking Her Blonde Sex DollAngelina    (91.1 MiB | 480x272 | 29min 48s | MPEG-4) \nhttp://imgfapper.com/img-56422dd5ae23b.html","torrent":{"xt":"urn:btih:5a94fdb8eba811f05dbb61592953b4a43007aed8","amp;dn":"Fucking+Her+Blonde+Sex+Doll+Angelina+PIR%40TE","amp;tr":["udp%3A%2F%2Ftracker.leechers-paradise.org%3A6969","udp%3A%2F%2Fzer0day.ch%3A1337","udp%3A%2F%2Fopen.demonii.com%3A1337","udp%3A%2F%2Ftracker.coppersurfer.tk%3A6969","udp%3A%2F%2Fexodus.desync.com%3A6969"],"infoHash":"5a94fdb8eba811f05dbb61592953b4a43007aed8","infoHashBuffer":{"type":"Buffer","data":[90,148,253,184,235,168,17,240,93,187,97,89,41,83,180,164,48,7,174,216]},"announce":[],"urlList":[]}}