{"title":"VA-Absolute_Summer_Hits_(Bonus_CD)_(MegaMix_By_DJ_MICHO)-2008-FD","uid":4193027,"size":84422239,"categoryP":"audio","categoryS":"music","magnet":"?xt=urn:btih:5caff10abd6c563ac36afb9180a75add02881189&amp;dn=VA-Absolute_Summer_Hits_%28Bonus_CD%29_%28MegaMix_By_DJ_MICHO%29-2008-FD&amp;tr=udp%3A%2F%2Ftracker.openbittorrent.com%3A80&amp;tr=udp%3A%2F%2Fopen.demonii.com%3A1337&amp;tr=udp%3A%2F%2Ftracker.coppersurfer.tk%3A6969&amp;tr=udp%3A%2F%2Fexodus.desync.com%3A6969","seeders":0,"leechers":0,"uploader":"DJMICHO","files":4,"time":1211062933,"description":"&amp;#039;&amp;#039;&amp;#039;&amp;#039;&amp;#039;&amp;#039;&amp;#039;&amp;#039;&amp;#039;&amp;#039;&amp;#039;&amp;#039;&amp;#039;&amp;#039;&amp;#039;&amp;#039;&amp;#039;&amp;#039;&amp;#039;&amp;#039;&amp;#039;&amp;#039;&amp;#039;&amp;#039;&amp;#039;&amp;#039;&amp;#039;&amp;#039;&amp;#039;&amp;#039;&amp;#039;&amp;#039;&amp;#039;&amp;#039;&amp;#039;&amp;#039;&amp;#039;&amp;#039;&amp;#039;&amp;#039;&amp;#039;&amp;#039;&amp;#039;&amp;#039;&amp;#039;&amp;#039;&amp;#039;&amp;#039;&amp;#039;&amp;#039;&amp;#039;&amp;#039;&amp;#039;&amp;#039;&amp;#039;&amp;#039;&amp;#039;&amp;#039;&amp;#039;&amp;#039;&amp;#039;&amp;#039;&amp;#039;&amp;#039;&amp;#039;&amp;#039;&amp;#039;&amp;#039;&amp;#039;&amp;#039;&amp;#039;&amp;#039;&amp;#039;&amp;#039;&amp;#039;&amp;#039;&amp;#039;&amp;#039;&amp;#039;\n       VA-Absolute Summer Hits (Bonus CD) (MegaMix By DJ MICHO)-2008-FDM\n&amp;#039;&amp;#039;&amp;#039;&amp;#039;&amp;#039;&amp;#039;&amp;#039;&amp;#039;&amp;#039;&amp;#039;&amp;#039;&amp;#039;&amp;#039;&amp;#039;&amp;#039;&amp;#039;&amp;#039;&amp;#039;&amp;#039;&amp;#039;&amp;#039;&amp;#039;&amp;#039;&amp;#039;&amp;#039;&amp;#039;&amp;#039;&amp;#039;&amp;#039;&amp;#039;&amp;#039;&amp;#039;&amp;#039;&amp;#039;&amp;#039;&amp;#039;&amp;#039;&amp;#039;&amp;#039;&amp;#039;&amp;#039;&amp;#039;&amp;#039;&amp;#039;&amp;#039;&amp;#039;&amp;#039;&amp;#039;&amp;#039;&amp;#039;&amp;#039;&amp;#039;&amp;#039;&amp;#039;&amp;#039;&amp;#039;&amp;#039;&amp;#039;&amp;#039;&amp;#039;&amp;#039;&amp;#039;&amp;#039;&amp;#039;&amp;#039;&amp;#039;&amp;#039;&amp;#039;&amp;#039;&amp;#039;&amp;#039;&amp;#039;&amp;#039;&amp;#039;&amp;#039;&amp;#039;&amp;#039;&amp;#039;&amp;#039;\n                              FREE DJ MUSIC - FDM\n-------------------------------------------------------------------------------\n\nTitle................: Absolute Summer Hits (Bonus CD) (MegaMix By DJ MICHO)\nArtist...............: Various Artists (VA)\nYear.................: 2008\nGenre................: Trance/Dance/House\nType.................: Self-made Mix.\nNumber of Songs......: 8\nSize.................: 84 MB\nRipdate..............: 17/may/2008\nReleasedate..........: 17/may/2008\n\nAudio Format.........: MP3\nRipper...............: VirtualCD\nBitrate..............: 256 \nHz...................: 44,100\nChannels.............: Stereo\nSource...............: ----\n\n-------------------------------------------------------------------------------\n\n  101-va-absolute_summer_hits__bonus_cd__megamix_by_dj_micho-2008-fdm\n      (00:43:58min)  (84 MB)\n\n-------------------------------------------------------------------------------\n  TrackList:\n  101-Cascada - Because The Night (Michael Kovacs Mix)\n  102-The Nightcrawlers - Push The Feeling On (Robbie Rivera Juicy Ibiza Mix)\n  103-Bronko - Dont Go (Michael Mind Mix)\n  104-The Rickrollerz - Never Gonna Give You Up (Johnny Phonetti Mix)\n  105-David Guetta Ft. Tara Mcdonald - Delirious ( Laidback Luke Remix)\n  106-Fabrizio E Marco - Fly Away (Crom &amp; Steel Extended Mix)\n  107-Tiesto Ft. Maxi Jazz - Dance4life (Sander Van Doorn Remix)\n  108-John Marks Ft. Blain - What Do You Say (Big Room Remix)\n\n-------------------------------------------------------------------------------\n                              FREE DJ MUSIC - FDM\n&amp;#039;&amp;#039;&amp;#039;&amp;#039;&amp;#039;&amp;#039;&amp;#039;&amp;#039;&amp;#039;&amp;#039;&amp;#039;&amp;#039;&amp;#039;&amp;#039;&amp;#039;&amp;#039;&amp;#039;&amp;#039;&amp;#039;&amp;#039;&amp;#039;&amp;#039;&amp;#039;&amp;#039;&amp;#039;&amp;#039;&amp;#039;&amp;#039;&amp;#039;&amp;#039;&amp;#039;&amp;#039;&amp;#039;&amp;#039;&amp;#039;&amp;#039;&amp;#039;&amp;#039;&amp;#039;&amp;#039;&amp;#039;&amp;#039;&amp;#039;&amp;#039;&amp;#039;&amp;#039;&amp;#039;&amp;#039;&amp;#039;&amp;#039;&amp;#039;&amp;#039;&amp;#039;&amp;#039;&amp;#039;&amp;#039;&amp;#039;&amp;#039;&amp;#039;&amp;#039;&amp;#039;&amp;#039;&amp;#039;&amp;#039;&amp;#039;&amp;#039;&amp;#039;&amp;#039;&amp;#039;&amp;#039;&amp;#039;&amp;#039;&amp;#039;&amp;#039;&amp;#039;&amp;#039;&amp;#039;&amp;#039;&amp;#039;\n       VA-Absolute Summer Hits (Bonus CD) (MegaMix By DJ MICHO)-2008-FDM\n&amp;#039;&amp;#039;&amp;#039;&amp;#039;&amp;#039;&amp;#039;&amp;#039;&amp;#039;&amp;#039;&amp;#039;&amp;#039;&amp;#039;&amp;#039;&amp;#039;&amp;#039;&amp;#039;&amp;#039;&amp;#039;&amp;#039;&amp;#039;&amp;#039;&amp;#039;&amp;#039;&amp;#039;&amp;#039;&amp;#039;&amp;#039;&amp;#039;&amp;#039;&amp;#039;&amp;#039;&amp;#039;&amp;#039;&amp;#039;&amp;#039;&amp;#039;&amp;#039;&amp;#039;&amp;#039;&amp;#039;&amp;#039;&amp;#039;&amp;#039;&amp;#039;&amp;#039;&amp;#039;&amp;#039;&amp;#039;&amp;#039;&amp;#039;&amp;#039;&amp;#039;&amp;#039;&amp;#039;&amp;#039;&amp;#039;&amp;#039;&amp;#039;&amp;#039;&amp;#039;&amp;#039;&amp;#039;&amp;#039;&amp;#039;&amp;#039;&amp;#039;&amp;#039;&amp;#039;&amp;#039;&amp;#039;&amp;#039;&amp;#039;&amp;#039;&amp;#039;&amp;#039;&amp;#039;&amp;#039;&amp;#039;&amp;#039;","torrent":{"xt":"urn:btih:5caff10abd6c563ac36afb9180a75add02881189","amp;dn":"VA-Absolute_Summer_Hits_%28Bonus_CD%29_%28MegaMix_By_DJ_MICHO%29-2008-FD","amp;tr":["udp%3A%2F%2Ftracker.openbittorrent.com%3A80","udp%3A%2F%2Fopen.demonii.com%3A1337","udp%3A%2F%2Ftracker.coppersurfer.tk%3A6969","udp%3A%2F%2Fexodus.desync.com%3A6969"],"infoHash":"5caff10abd6c563ac36afb9180a75add02881189","infoHashBuffer":{"type":"Buffer","data":[92,175,241,10,189,108,86,58,195,106,251,145,128,167,90,221,2,136,17,137]},"announce":[],"urlList":[]}}