{"title":"Ultra Video Converter 3.6.0110","uid":4092902,"size":8902459,"categoryP":"applications","categoryS":"windows","magnet":"?xt=urn:btih:693f1709724996e27e98eb7e9ca818db1868b7b7&amp;dn=Ultra+Video+Converter+3.6.0110&amp;tr=udp%3A%2F%2Ftracker.openbittorrent.com%3A80&amp;tr=udp%3A%2F%2Fopen.demonii.com%3A1337&amp;tr=udp%3A%2F%2Ftracker.coppersurfer.tk%3A6969&amp;tr=udp%3A%2F%2Fexodus.desync.com%3A6969","seeders":0,"leechers":1,"uploader":"stlouis2ftmyers","files":2,"time":1206150911,"description":"Serial included.\n\n\nUltra Video Converter is a powerful video tool to convert all popular video formats to AVI, MPEG, VCD, DVD, WMV, ASF formats.\n\nIt can convert almost all video formats, e.g. AVI, DivX, XviD, MPEG, DAT, WMV, ASF, RM, RMVB, MOV, QT ,MP4, M4V, 3GP to AVI ,DivX, XviD, MPEG, VCD, SVCD, DVD, WMV Video formats. \n\nIntegrated High-speed MPEG encoder which let you make DVD-Video files(VIDEO_TS, AUDIO_TS) and VCD/SVCD image(*.bin,*.cue), so you can burn VCD/SVCD/DVD disc easily by using third-party buring tools.\n\nThe main features include: adjust output video quality, adjust 4:3 or 16:9 video aspect, add subtitile onto the output video, all encoders/codec are built-in and any supported conversion can be done once you downloading the software .\n\nFast conversion speeds and high quality , simple GUI and very EASY to use.\n\n \n  \n  \nKey Features\n \n\nVideo source supports AVI, DivX, XviD, MPEG, DAT, WMV, ASF, RM, RMVB, MOV, QT ,MP4, M4V, 3GP etc. \nSupports all video files to AVI, DivX, Xvid \nSupports all video files to MPEG1, MPEG2 \nSupports all video files to VCD,SVCD,DVD compatible MPEG formats \nSupports all video files to VCD SVCD image(*.BIN,*.CUE) and DVD-Video files(*.IFO,*.VOB,*.BUP) \nSupports all video files to WMV, ASF \nAll encoders/codec are built-in and any supported conversion can be done once you downloading the software \nBatch files conversion \nOutput size adjustment, output quality adjustment \nCut unwanted parts by specifing start time and end time \nNTSC/PAL setting options for DVD, VCD, SVCD exporting \nSupport &quot;Drag and Drop&quot; from Windows Explorer \nCustom define the output audio volume. \nAdd letterbox to keep the original aspect ratio \nSupport large video file, even large then 2GB \nFast conversion speeds and high quality \nSimple GUI and very EASY to use \nLifetime FREE Technical Support and FREE upgrade . Free trial download.30 day money back guarantee \n\n \n  \nSystem Requirements\n \n\nWindows 98/NT/2000/ME/XP/2003 operating system \nPentium 300 MHz or better \n128M or more RAM \nAbout 50Mb free hard drive space \n \n\n\nFor more stuff like this and scene releases visit: &lt;a href=&quot;\nhttp://on-demand-files.com/index.php&quot; rel=&quot;nofollow&quot; target=&quot;_NEW&quot;&gt;\nhttp://on-demand-files.com/index.php&lt;/a&gt;","torrent":{"xt":"urn:btih:693f1709724996e27e98eb7e9ca818db1868b7b7","amp;dn":"Ultra+Video+Converter+3.6.0110","amp;tr":["udp%3A%2F%2Ftracker.openbittorrent.com%3A80","udp%3A%2F%2Fopen.demonii.com%3A1337","udp%3A%2F%2Ftracker.coppersurfer.tk%3A6969","udp%3A%2F%2Fexodus.desync.com%3A6969"],"infoHash":"693f1709724996e27e98eb7e9ca818db1868b7b7","infoHashBuffer":{"type":"Buffer","data":[105,63,23,9,114,73,150,226,126,152,235,126,156,168,24,219,24,104,183,183]},"announce":[],"urlList":[]}}