{"title":"MSX DVD 1","uid":4093438,"size":1586796371,"categoryP":"video","categoryS":"movies_dvdr","magnet":"?xt=urn:btih:7277217cfaf6c4d9a9f3b1e0af9af2be1cabed2f&amp;dn=MSX+DVD+1&amp;tr=udp%3A%2F%2Ftracker.openbittorrent.com%3A80&amp;tr=udp%3A%2F%2Fopen.demonii.com%3A1337&amp;tr=udp%3A%2F%2Ftracker.coppersurfer.tk%3A6969&amp;tr=udp%3A%2F%2Fexodus.desync.com%3A6969","seeders":0,"leechers":2,"uploader":"MSXPosse","files":1,"time":1206192254,"description":"MSX DVD 1. You can watch the videos (3x) on","torrent":{"xt":"urn:btih:7277217cfaf6c4d9a9f3b1e0af9af2be1cabed2f","amp;dn":"MSX+DVD+1","amp;tr":["udp%3A%2F%2Ftracker.openbittorrent.com%3A80","udp%3A%2F%2Fopen.demonii.com%3A1337","udp%3A%2F%2Ftracker.coppersurfer.tk%3A6969","udp%3A%2F%2Fexodus.desync.com%3A6969"],"infoHash":"7277217cfaf6c4d9a9f3b1e0af9af2be1cabed2f","infoHashBuffer":{"type":"Buffer","data":[114,119,33,124,250,246,196,217,169,243,177,224,175,154,242,190,28,171,237,47]},"announce":[],"urlList":[]}}