{"title":"LabÂ° - Dubalgan 500 Mg (FLAC)","uid":4210835,"size":286484713,"categoryP":"audio","categoryS":"flac","magnet":"?xt=urn:btih:78d3fb5ad77281de5fc73a13e479e20fa3e2f829&amp;dn=Lab%C2%B0+-+Dubalgan+500+Mg+%28FLAC%29&amp;tr=udp%3A%2F%2Ftracker.openbittorrent.com%3A80&amp;tr=udp%3A%2F%2Fopen.demonii.com%3A1337&amp;tr=udp%3A%2F%2Ftracker.coppersurfer.tk%3A6969&amp;tr=udp%3A%2F%2Fexodus.desync.com%3A6969","seeders":0,"leechers":0,"uploader":"JAMBONNEAU","files":8,"time":1212019263,"description":" &lt;a href=&quot;http://www.discogs.com/release/1330369&quot; rel=&quot;nofollow&quot; target=&quot;_NEW&quot;&gt;http://www.discogs.com/release/1330369&lt;/a&gt;","torrent":{"xt":"urn:btih:78d3fb5ad77281de5fc73a13e479e20fa3e2f829","amp;dn":"Lab%C2%B0+-+Dubalgan+500+Mg+%28FLAC%29","amp;tr":["udp%3A%2F%2Ftracker.openbittorrent.com%3A80","udp%3A%2F%2Fopen.demonii.com%3A1337","udp%3A%2F%2Ftracker.coppersurfer.tk%3A6969","udp%3A%2F%2Fexodus.desync.com%3A6969"],"infoHash":"78d3fb5ad77281de5fc73a13e479e20fa3e2f829","infoHashBuffer":{"type":"Buffer","data":[120,211,251,90,215,114,129,222,95,199,58,19,228,121,226,15,163,226,248,41]},"announce":[],"urlList":[]}}