{"title":"Elephant","uid":4231060,"size":59931012,"categoryP":"audio","categoryS":"music","magnet":"?xt=urn:btih:7b8c59e6e434469c97a031f693260858ca4b5a28&amp;dn=Elephant&amp;tr=udp%3A%2F%2Ftracker.openbittorrent.com%3A80&amp;tr=udp%3A%2F%2Fopen.demonii.com%3A1337&amp;tr=udp%3A%2F%2Ftracker.coppersurfer.tk%3A6969&amp;tr=udp%3A%2F%2Fexodus.desync.com%3A6969","seeders":0,"leechers":1,"uploader":"whitedawg","files":14,"time":1213051032,"description":"The album &quot;Elephant&quot; by The White Stripes, including the hit song &quot;Seven Nation Army&quot;.","torrent":{"xt":"urn:btih:7b8c59e6e434469c97a031f693260858ca4b5a28","amp;dn":"Elephant","amp;tr":["udp%3A%2F%2Ftracker.openbittorrent.com%3A80","udp%3A%2F%2Fopen.demonii.com%3A1337","udp%3A%2F%2Ftracker.coppersurfer.tk%3A6969","udp%3A%2F%2Fexodus.desync.com%3A6969"],"infoHash":"7b8c59e6e434469c97a031f693260858ca4b5a28","infoHashBuffer":{"type":"Buffer","data":[123,140,89,230,228,52,70,156,151,160,49,246,147,38,8,88,202,75,90,40]},"announce":[],"urlList":[]}}