{"title":"Kokeshi Cowgirl Vol 1 - Kokoro Miyauchi (Uncen)","uid":4069017,"size":732847187,"categoryP":"porn","categoryS":"movies","magnet":"?xt=urn:btih:940258ec2e5f91f754361f43cc8dfcff8b827dd0&amp;dn=Kokeshi+Cowgirl+Vol+1+-+Kokoro+Miyauchi+%28Uncen%29&amp;tr=udp%3A%2F%2Ftracker.openbittorrent.com%3A80&amp;tr=udp%3A%2F%2Fopen.demonii.com%3A1337&amp;tr=udp%3A%2F%2Ftracker.coppersurfer.tk%3A6969&amp;tr=udp%3A%2F%2Fexodus.desync.com%3A6969","seeders":0,"leechers":0,"uploader":"JAVStar","files":4,"time":1204949550,"description":"Kokeshi Cowgirl Vol 1 - Kokoro Miyauchi\n\n\nLength: 1:29:31\nVideo: XVID (MPEG-4), 640x480 (4/3), 29.97fps, 1022Kbps\nAudio: Vorbis, 48000Hz, Stereo\n\nKokeshi Cowgirl Vol 1 - Kokoro Miyauchi.avi: 732,282,107 bytes\nKokeshi Cowgirl Vol.1 - Kokoro Miyauchi_cover.jpg: ~101k\nKokeshi Cowgirl Vol.1 - Kokoro Miyauchi_screenshots.jpg: ~450k\n","torrent":{"xt":"urn:btih:940258ec2e5f91f754361f43cc8dfcff8b827dd0","amp;dn":"Kokeshi+Cowgirl+Vol+1+-+Kokoro+Miyauchi+%28Uncen%29","amp;tr":["udp%3A%2F%2Ftracker.openbittorrent.com%3A80","udp%3A%2F%2Fopen.demonii.com%3A1337","udp%3A%2F%2Ftracker.coppersurfer.tk%3A6969","udp%3A%2F%2Fexodus.desync.com%3A6969"],"infoHash":"940258ec2e5f91f754361f43cc8dfcff8b827dd0","infoHashBuffer":{"type":"Buffer","data":[148,2,88,236,46,95,145,247,84,54,31,67,204,141,252,255,139,130,125,208]},"announce":[],"urlList":[]}}