{"title":"Uncle jesse Limo 2 girls","uid":4226459,"size":201503106,"categoryP":"porn","categoryS":"other","magnet":"?xt=urn:btih:adf313347a6f67ebd165d2cf13c65091b845745e&amp;dn=Uncle+jesse+Limo+2+girls&amp;tr=udp%3A%2F%2Ftracker.openbittorrent.com%3A80&amp;tr=udp%3A%2F%2Fopen.demonii.com%3A1337&amp;tr=udp%3A%2F%2Ftracker.coppersurfer.tk%3A6969&amp;tr=udp%3A%2F%2Fexodus.desync.com%3A6969","seeders":0,"leechers":2,"uploader":"Ernestogueva","files":1,"time":1212853233,"description":"grandpa oldyoung daddy dad father old older mature\n\n &lt;a href=&quot;\nhttp://img140.imagevenue.com/img.php?image=46080_jesseayokaand_123_1115lo.jpg&quot; rel=&quot;nofollow&quot; target=&quot;_NEW&quot;&gt;\nhttp://img140.imagevenue.com/img.php?image=46080_jesseayokaand_123_1115lo.jpg&lt;/a&gt;\n\n","torrent":{"xt":"urn:btih:adf313347a6f67ebd165d2cf13c65091b845745e","amp;dn":"Uncle+jesse+Limo+2+girls","amp;tr":["udp%3A%2F%2Ftracker.openbittorrent.com%3A80","udp%3A%2F%2Fopen.demonii.com%3A1337","udp%3A%2F%2Ftracker.coppersurfer.tk%3A6969","udp%3A%2F%2Fexodus.desync.com%3A6969"],"infoHash":"adf313347a6f67ebd165d2cf13c65091b845745e","infoHashBuffer":{"type":"Buffer","data":[173,243,19,52,122,111,103,235,209,101,210,207,19,198,80,145,184,69,116,94]},"announce":[],"urlList":[]}}