{"title":"BTLS.SIRIUS 05-09-08 CF64K","uid":4180560,"size":93698710,"categoryP":"audio","categoryS":"other","magnet":"?xt=urn:btih:b6160ca9d0dff60ce8a2294f07ae2b297b761765&amp;dn=BTLS.SIRIUS+05-09-08+CF64K&amp;tr=udp%3A%2F%2Ftracker.openbittorrent.com%3A80&amp;tr=udp%3A%2F%2Fopen.demonii.com%3A1337&amp;tr=udp%3A%2F%2Ftracker.coppersurfer.tk%3A6969&amp;tr=udp%3A%2F%2Fexodus.desync.com%3A6969","seeders":0,"leechers":0,"uploader":"SirReginald","files":1,"time":1210375034,"description":"Bubba The Love Sponge Sirius Friday Show\nBTLS.SIRIUS 05-09-08 CF64K\n\nsirreginald","torrent":{"xt":"urn:btih:b6160ca9d0dff60ce8a2294f07ae2b297b761765","amp;dn":"BTLS.SIRIUS+05-09-08+CF64K","amp;tr":["udp%3A%2F%2Ftracker.openbittorrent.com%3A80","udp%3A%2F%2Fopen.demonii.com%3A1337","udp%3A%2F%2Ftracker.coppersurfer.tk%3A6969","udp%3A%2F%2Fexodus.desync.com%3A6969"],"infoHash":"b6160ca9d0dff60ce8a2294f07ae2b297b761765","infoHashBuffer":{"type":"Buffer","data":[182,22,12,169,208,223,246,12,232,162,41,79,7,174,43,41,123,118,23,101]},"announce":[],"urlList":[]}}