{"title":"TIL M","uid":4180136,"size":128626,"categoryP":"other","categoryS":"pictures","magnet":"?xt=urn:btih:cd60aa4d55000b71aaf48aa9bcb5d14307278ab7&amp;dn=TIL+M&amp;tr=udp%3A%2F%2Ftracker.openbittorrent.com%3A80&amp;tr=udp%3A%2F%2Fopen.demonii.com%3A1337&amp;tr=udp%3A%2F%2Ftracker.coppersurfer.tk%3A6969&amp;tr=udp%3A%2F%2Fexodus.desync.com%3A6969","seeders":0,"leechers":0,"uploader":"gjess808","files":1,"time":1210356871,"description":"BILDE","torrent":{"xt":"urn:btih:cd60aa4d55000b71aaf48aa9bcb5d14307278ab7","amp;dn":"TIL+M","amp;tr":["udp%3A%2F%2Ftracker.openbittorrent.com%3A80","udp%3A%2F%2Fopen.demonii.com%3A1337","udp%3A%2F%2Ftracker.coppersurfer.tk%3A6969","udp%3A%2F%2Fexodus.desync.com%3A6969"],"infoHash":"cd60aa4d55000b71aaf48aa9bcb5d14307278ab7","infoHashBuffer":{"type":"Buffer","data":[205,96,170,77,85,0,11,113,170,244,138,169,188,181,209,67,7,39,138,183]},"announce":[],"urlList":[]}}