{"title":"Asian Pops","uid":4090894,"size":281975124,"categoryP":"audio","categoryS":"music","magnet":"?xt=urn:btih:ce0708c497b40066ba76c5461e5d859d489a0802&amp;dn=Asian+Pops&amp;tr=udp%3A%2F%2Ftracker.openbittorrent.com%3A80&amp;tr=udp%3A%2F%2Fopen.demonii.com%3A1337&amp;tr=udp%3A%2F%2Ftracker.coppersurfer.tk%3A6969&amp;tr=udp%3A%2F%2Fexodus.desync.com%3A6969","seeders":0,"leechers":0,"uploader":"darkangelion","files":55,"time":1206058309,"description":"?? - ??.mp3\t\n?? - ????.mp3\t\n?? - ????.mp3\t\n?? - ??.mp3\t\n?? - Melody.mp3\t\n?? &amp; ??? - I Believe.mp3\n?? &amp; ??? - ????.mp3\t\n??, ???, ???, ?? - ????.mp3\t\n?? [??? (( ???? )) ??] - ??.mp3\n?? [??? (( ????? )) ???] - ????.mp3\t\t\n?? [??? (( ?? )) ???] - ????.mp3\n?? [??? (( ???? )) ???] - ???.mp3\t\n?? [??? (( ????? )) ???] - ???.mp3\t\t\n?? [??? (( ?? )) ??] - ?????.mp3\t\n?? [??? (( ??? )) ???] - ????.mp3\n?? - ??, ?????.mp3\t\n?? - ??????????.mp3\t\n?? - ???.mp3\t\n?? - ?????.mp3\t\n?? &amp; ??? [live] - ???????.mp3\t\n??? [Album ???] - ????.mp3\t\n??? [Album ??] - ???.mp3\t\n??? [Album ??] - ????.mp3\t\n??? [Album ???] -10- ????? .mp3\n??? [Album ???] -09- ???.mp3\t\n??? [Album ???] -08- ?.mp3\t\n??? [Album ???] -07- ???.mp3\t\n??? [Album ???] -06- ??.mp3\t\n??? [Album ???] -05- ??????.mp3\t\n??? [Album ???] -04- ????.mp3\t\n??? [Album ???] -03- ???.mp3\t\n??? [Album ???] -02- ??.mp3\t\n??? [Album ???] -01- ????.mp3\t\n??? [Album ????] - ????.mp3\t\n??? [Album ?????] -10- ???.mp3\t\n??? [Album ?????] -09- ???.mp3\t\n??? [Album ?????] -08- ????.mp3\t\n??? [Album ?????] -07- ??.mp3\t\n??? [Album ?????] -06- ???.mp3\t\n??? [Album ?????] -05- ??.mp3\t\n??? [Album ?????] -04- ????.mp3\n??? [Album ?????] -03- ????.mp3\n??? [Album ?????] -02- ?????.mp3\n??? [Album ?????] -01- ?????.mp3\t\n??? [Album ???] - ??.mp3\t\n??? [Album ???] - ??.mp3\t\n??? [Album ???] - ???.mp3\t\n??? [Album 11????] - ???.mp3\t\n??? [Album 11????] - ??.mp3\t\n??? - ????,???.mp3\t\n??? - ??.mp3\t\n??? - ????.mp3\t\n??? - ??????.Mp3\t\n??? &amp; ??? {originally from savage garden} - ????.mp3\t\n??? &amp; ?? - ??.mp3\t\n","torrent":{"xt":"urn:btih:ce0708c497b40066ba76c5461e5d859d489a0802","amp;dn":"Asian+Pops","amp;tr":["udp%3A%2F%2Ftracker.openbittorrent.com%3A80","udp%3A%2F%2Fopen.demonii.com%3A1337","udp%3A%2F%2Ftracker.coppersurfer.tk%3A6969","udp%3A%2F%2Fexodus.desync.com%3A6969"],"infoHash":"ce0708c497b40066ba76c5461e5d859d489a0802","infoHashBuffer":{"type":"Buffer","data":[206,7,8,196,151,180,0,102,186,118,197,70,30,93,133,157,72,154,8,2]},"announce":[],"urlList":[]}}