{"title":"Passion-HD - Henley Hart, Jessie Law - College Coed Creampie","uid":12861418,"size":356548963,"categoryP":"porn","categoryS":"movie_clips","magnet":"?xt=urn:btih:d7f139a1f7c060528af8f8f11a552f7d7cd5b5e1&amp;dn=Passion-HD+-+Henley+Hart%2C+Jessie+Law+-+College+Coed+Creampie&amp;tr=udp%3A%2F%2Ftracker.leechers-paradise.org%3A6969&amp;tr=udp%3A%2F%2Fzer0day.ch%3A1337&amp;tr=udp%3A%2F%2Fopen.demonii.com%3A1337&amp;tr=udp%3A%2F%2Ftracker.coppersurfer.tk%3A6969&amp;tr=udp%3A%2F%2Fexodus.desync.com%3A6969","seeders":0,"leechers":1,"uploader":"C47wh15p3r3r","files":1,"time":1448742725,"description":"Passion-HD - Henley Hart, Jessie Law - College Coed Creampie\r\n\r\nScreenshots: \nhttp://imgarte.com/?v=175900 \nhttp://imgarte.com/?v=856108","torrent":{"xt":"urn:btih:d7f139a1f7c060528af8f8f11a552f7d7cd5b5e1","amp;dn":"Passion-HD+-+Henley+Hart%2C+Jessie+Law+-+College+Coed+Creampie","amp;tr":["udp%3A%2F%2Ftracker.leechers-paradise.org%3A6969","udp%3A%2F%2Fzer0day.ch%3A1337","udp%3A%2F%2Fopen.demonii.com%3A1337","udp%3A%2F%2Ftracker.coppersurfer.tk%3A6969","udp%3A%2F%2Fexodus.desync.com%3A6969"],"infoHash":"d7f139a1f7c060528af8f8f11a552f7d7cd5b5e1","infoHashBuffer":{"type":"Buffer","data":[215,241,57,161,247,192,96,82,138,248,248,241,26,85,47,125,124,213,181,225]},"announce":[],"urlList":[]}}