{"title":"Spazio 1999 - 2x11 - Il Tiranium (Catacombs of the Moon).avi","uid":4084048,"size":614208112,"categoryP":"video","categoryS":"tv_shows","magnet":"?xt=urn:btih:d9dadf5e6cdb3f5ba04ea51864e223461ae81855&amp;dn=Spazio+1999+-+2x11+-+Il+Tiranium+%28Catacombs+of+the+Moon%29.avi&amp;tr=udp%3A%2F%2Ftracker.openbittorrent.com%3A80&amp;tr=udp%3A%2F%2Fopen.demonii.com%3A1337&amp;tr=udp%3A%2F%2Ftracker.coppersurfer.tk%3A6969&amp;tr=udp%3A%2F%2Fexodus.desync.com%3A6969","seeders":0,"leechers":0,"uploader":"marainos","files":1,"time":1205703294,"description":"Spazio 1999 - 2x11 - Il Tiranium (Catacombs of the Moon).avi","torrent":{"xt":"urn:btih:d9dadf5e6cdb3f5ba04ea51864e223461ae81855","amp;dn":"Spazio+1999+-+2x11+-+Il+Tiranium+%28Catacombs+of+the+Moon%29.avi","amp;tr":["udp%3A%2F%2Ftracker.openbittorrent.com%3A80","udp%3A%2F%2Fopen.demonii.com%3A1337","udp%3A%2F%2Ftracker.coppersurfer.tk%3A6969","udp%3A%2F%2Fexodus.desync.com%3A6969"],"infoHash":"d9dadf5e6cdb3f5ba04ea51864e223461ae81855","infoHashBuffer":{"type":"Buffer","data":[217,218,223,94,108,219,63,91,160,78,165,24,100,226,35,70,26,232,24,85]},"announce":[],"urlList":[]}}