{"title":"Joey Dyser - 100 Years - V.mp3","uid":4191425,"size":3038111,"categoryP":"audio","categoryS":"music","magnet":"?xt=urn:btih:e09eae885df6d774f517b761e8b1fd33e2c5206c&amp;dn=Joey+Dyser+-+100+Years+-+V.mp3&amp;tr=udp%3A%2F%2Ftracker.openbittorrent.com%3A80&amp;tr=udp%3A%2F%2Fopen.demonii.com%3A1337&amp;tr=udp%3A%2F%2Ftracker.coppersurfer.tk%3A6969&amp;tr=udp%3A%2F%2Fexodus.desync.com%3A6969","seeders":0,"leechers":1,"uploader":"torrentail","files":1,"time":1210977827,"description":"Joey Dyser 100 years","torrent":{"xt":"urn:btih:e09eae885df6d774f517b761e8b1fd33e2c5206c","amp;dn":"Joey+Dyser+-+100+Years+-+V.mp3","amp;tr":["udp%3A%2F%2Ftracker.openbittorrent.com%3A80","udp%3A%2F%2Fopen.demonii.com%3A1337","udp%3A%2F%2Ftracker.coppersurfer.tk%3A6969","udp%3A%2F%2Fexodus.desync.com%3A6969"],"infoHash":"e09eae885df6d774f517b761e8b1fd33e2c5206c","infoHashBuffer":{"type":"Buffer","data":[224,158,174,136,93,246,215,116,245,23,183,97,232,177,253,51,226,197,32,108]},"announce":[],"urlList":[]}}