{"title":"Kush.2007.DVDRip.XviD-VoMiT.[avi-release]","uid":4220285,"size":764753202,"categoryP":"video","categoryS":"movies","magnet":"?xt=urn:btih:e52a4fe93cb01da1dc98de7fc89c7775f6d4cf15&amp;dn=Kush.2007.DVDRip.XviD-VoMiT.%5Bavi-release%5D&amp;tr=udp%3A%2F%2Ftracker.openbittorrent.com%3A80&amp;tr=udp%3A%2F%2Fopen.demonii.com%3A1337&amp;tr=udp%3A%2F%2Ftracker.coppersurfer.tk%3A6969&amp;tr=udp%3A%2F%2Fexodus.desync.com%3A6969","seeders":0,"leechers":1,"uploader":"avi-torrents","files":55,"time":1212555107,"description":"Release Group: VoMiT\nRelease Name: Kush.2007.DVDRip.XviD-VoMiT\nSource: DVD\nSize: 729.33 MB\nGenre: Action / Adventure\nVideo: XviD, 624 x 336, 957 kbps\nAudio: MP3 VBR Stereo, 120 kbps\nRuntime: 89 minutes\nIMDB Rating: 3.1/10 (6 votes)\nDirected by: York Shackleton\nStarring: William Atherton, Lin Shaye, James Duval, Marnette Patterson, Matthew Carey\n\nA group of young drug dealers make the biggest mistake of their lives when they front a 10-pack of Kush to a risky crack-head. Burned out of thirty thousand dollars they take matters into their own hands and scheme to kidnap the crack-head s teenage brother. But their perfect drug dealing money making life quickly falls apart and relationships even those bound by time and family are quickly destroyed.\n\nIMDb: http://www.imdb.com/title/tt0477138/","torrent":{"xt":"urn:btih:e52a4fe93cb01da1dc98de7fc89c7775f6d4cf15","amp;dn":"Kush.2007.DVDRip.XviD-VoMiT.%5Bavi-release%5D","amp;tr":["udp%3A%2F%2Ftracker.openbittorrent.com%3A80","udp%3A%2F%2Fopen.demonii.com%3A1337","udp%3A%2F%2Ftracker.coppersurfer.tk%3A6969","udp%3A%2F%2Fexodus.desync.com%3A6969"],"infoHash":"e52a4fe93cb01da1dc98de7fc89c7775f6d4cf15","infoHashBuffer":{"type":"Buffer","data":[229,42,79,233,60,176,29,161,220,152,222,127,200,156,119,117,246,212,207,21]},"announce":[],"urlList":[]}}