{"title":"Battlefield 2142 2.50 Incremental Patch Update","uid":4212988,"size":177567468,"categoryP":"games","categoryS":"pc","magnet":"?xt=urn:btih:f1dd391cf7ca676465c465a9e76deb73522eb651&amp;dn=Battlefield+2142+2.50+Incremental+Patch+Update&amp;tr=udp%3A%2F%2Ftracker.openbittorrent.com%3A80&amp;tr=udp%3A%2F%2Fopen.demonii.com%3A1337&amp;tr=udp%3A%2F%2Ftracker.coppersurfer.tk%3A6969&amp;tr=udp%3A%2F%2Fexodus.desync.com%3A6969","seeders":0,"leechers":0,"uploader":"anonfxx","files":1,"time":1212178557,"description":"The real deal. I downloaded it today, 5/30/2008.\n\nHopefully we&amp;#039;ll get enough seeds to make it faster to download than downloading it from EA.\n\nAnywho... This is the Incremental update from EA for patch 2.50. You have to already have 2.4 installed. (You really couldn&amp;#039;t have played the game in the last 6 months without it)\n\nVisit my friends blog: 365Discoveries.com","torrent":{"xt":"urn:btih:f1dd391cf7ca676465c465a9e76deb73522eb651","amp;dn":"Battlefield+2142+2.50+Incremental+Patch+Update","amp;tr":["udp%3A%2F%2Ftracker.openbittorrent.com%3A80","udp%3A%2F%2Fopen.demonii.com%3A1337","udp%3A%2F%2Ftracker.coppersurfer.tk%3A6969","udp%3A%2F%2Fexodus.desync.com%3A6969"],"infoHash":"f1dd391cf7ca676465c465a9e76deb73522eb651","infoHashBuffer":{"type":"Buffer","data":[241,221,57,28,247,202,103,100,101,196,101,169,231,109,235,115,82,46,182,81]},"announce":[],"urlList":[]}}