{"title":"The Walking Dead S06E07 720p 5.1Ch Web-DL ReEnc DeeJayAhmed","uid":12822840,"size":365178938,"categoryP":"video","categoryS":"hd___tv_shows","magnet":"?xt=urn:btih:f605f19bdfe24242261d40cf8f3fa4d0a475e224&amp;dn=The+Walking+Dead+S06E07+720p+5.1Ch+Web-DL+ReEnc+DeeJayAhmed&amp;tr=udp%3A%2F%2Ftracker.leechers-paradise.org%3A6969&amp;tr=udp%3A%2F%2Fzer0day.ch%3A1337&amp;tr=udp%3A%2F%2Fopen.demonii.com%3A1337&amp;tr=udp%3A%2F%2Ftracker.coppersurfer.tk%3A6969&amp;tr=udp%3A%2F%2Fexodus.desync.com%3A6969","seeders":0,"leechers":0,"uploader":"DeeJayPirate","files":4,"time":1448309526,"description":"DeeJayAhmed  \nhttps://www.DeeJayAhmed.com\r\r\nKeep Seeding!!=)) \r\nDo Comment On The A/V Quality Considering The Size Of The File..!\r\n\r\n\r\nFormat : Matroska\r\nLength : 348 MiB for 43mn 2s 260ms\r\n\r\nVideo #0 : AVC\r\nAspect : 1280 x 718 (1.783) at 23.976 fps\r\n\r\nAudio #0 : AAC\r\nInfos : 6 channels, 48.0 KHz / 24.0 KHz\r\nLanguage : en","torrent":{"xt":"urn:btih:f605f19bdfe24242261d40cf8f3fa4d0a475e224","amp;dn":"The+Walking+Dead+S06E07+720p+5.1Ch+Web-DL+ReEnc+DeeJayAhmed","amp;tr":["udp%3A%2F%2Ftracker.leechers-paradise.org%3A6969","udp%3A%2F%2Fzer0day.ch%3A1337","udp%3A%2F%2Fopen.demonii.com%3A1337","udp%3A%2F%2Ftracker.coppersurfer.tk%3A6969","udp%3A%2F%2Fexodus.desync.com%3A6969"],"infoHash":"f605f19bdfe24242261d40cf8f3fa4d0a475e224","infoHashBuffer":{"type":"Buffer","data":[246,5,241,155,223,226,66,66,38,29,64,207,143,63,164,208,164,117,226,36]},"announce":[],"urlList":[]}}